[
  {"word": "pan", "resources" : ["pan.png"] },
  {"word": "pin", "resources" : ["pin.jpg"] },
  {"word": "rub", "resources" : ["rub.gif"] },
  {"word": "rib", "resources" : ["ribs.png"] },
  {"word": "cup", "resources" : ["cup.png"] },
  {"word": "cap", "resources" : ["cap.png"] },
  {"word": "bag", "resources" : ["bag.png"] },
  {"word": "tag", "resources" : ["tag.png"] },
  {"word": "rag", "resources" : ["rag.png"] },
  {"word": "jam", "resources" : ["jam.png"] },
  {"word": "ram", "resources" : ["ram.png"] },
  {"word": "cab", "resources" : ["cab1.png", "cab2.png"] },
  {"word": "yam", "resources" : ["yam.png"] },
  {"word": "wax", "resources" : ["wax1.png", "wax2.png"] },
  {"word": "tax", "resources" : [] },
  {"word": "dam", "resources" : ["dam1.png", "dam2.png"] },
  {"word": "wag", "resources" : ["wag.gif"] },
  {"word": "book", "resources" : ["book.png"] },
  {"word": "hook", "resources" : ["hook.png"] },
  {"word": "cook", "resources" : ["cook1.png", "cook2.png"] },
  {"word": "moon", "resources" : ["moon.png"] },
  {"word": "look", "resources" : [] },
  {"word": "boon", "resources" : [] },
  {"word": "foot", "resources" : ["foot.png"] },
  {"word": "loot", "resources" : [] },
  {"word": "hood", "resources" : ["hood1.png", "hood2.png"] },
  {"word": "food", "resources" : ["food1.png", "food2.png"] },
  {"word": "root", "resources" : ["root1.png", "root2.gif"] },
  {"word": "zoom", "resources" : [] },
  {"word": "soon", "resources" : [] },
  {"word": "room", "resources" : ["room1.png", "room2.png"] },
  {"word": "good", "resources" : [] },
  {"word": "loom", "resources" : ["loom.png"] },
  {"word": "pool", "resources" : ["pool.png"] },
  {"word": "tool", "resources" : ["tool.png"] },
  {"word": "wool", "resources" : ["wool1.png", "wool2.png", "wool3.png"] },
  {"word": "see", "resources" : [] },
  {"word": "bee", "resources" : ["bee1.png", "bee2.png"] },
  {"word": "feet", "resources" : ["feet.png"] },
  {"word": "been", "resources" : [] },
  {"word": "seen", "resources" : [] },
  {"word": "feed", "resources" : ["feed1.gif", "feed2.gif"] },
  {"word": "seed", "resources" : ["seed1.png", "seed2.png"] },
  {"word": "weed", "resources" : ["weed1.png", "weed2.png"] },
  {"word": "deed", "resources" : [] },
  {"word": "teen", "resources" : [] },
  {"word": "pick", "resources" : ["pick.gif"] },
  {"word": "lick", "resources" : ["lick.gif"] },
  {"word": "sock", "resources" : ["sock.png"] },
  {"word": "duck", "resources" : ["duck.png"] },
  {"word": "hick", "resources" : [] },
  {"word": "jack", "resources" : ["jack1.png", "jack2.png"] },
  {"word": "pack", "resources" : ["pack.gif"] },
  {"word": "rack", "resources" : ["rack.png"] },
  {"word": "rock", "resources" : ["rock1.png", "rock2.png"] },
  {"word": "sick", "resources" : [] },
  {"word": "sack", "resources" : ["sack.png"] },
  {"word": "tack", "resources" : [] },
  {"word": "mock", "resources" : [] },
  {"word": "wack", "resources" : [] },
  {"word": "back", "resources" : [] },
  {"word": "buck", "resources" : ["buck.png"] },
  {"word": "cock", "resources" : ["cock.png"] },
  {"word": "lack", "resources" : [] },
  {"word": "lock", "resources" : ["lock.png"] },
  {"word": "nack", "resources" : [] },
  {"word": "hack", "resources" : [] },
  {"word": "nick", "resources" : [] },
  {"word": "chat", "resources" : [] },
  {"word": "chin", "resources" : ["chin.png"] },
  {"word": "chap", "resources" : [] },
  {"word": "check", "resources" : [] },
  {"word": "chop", "resources" : ["chop.gif"] },
  {"word": "cheese", "resources" : ["cheese.jpg"] },
  {"word": "rich", "resources" : [] },
  {"word": "such", "resources" : [] },
  {"word": "much", "resources" : [] },
  {"word": "itch", "resources" : [] },
  {"word": "church", "resources" : ["church1.jpg", "church2.jpg"] },
  {"word": "she", "resources" : [] },
  {"word": "shy", "resources" : [] },
  {"word": "shag", "resources" : [] },
  {"word": "sham", "resources" : [] },
  {"word": "shed", "resources" : ["shed.png"] },
  {"word": "shin", "resources" : ["shin.png"] },
  {"word": "ship", "resources" : ["ship.png"] },
  {"word": "shoe", "resources" : ["shoe.png"] },
  {"word": "shoo", "resources" : [] },
  {"word": "shop", "resources" : ["shop.png"] },
  {"word": "shot", "resources" : [] },
  {"word": "show", "resources" : [] },
  {"word": "shut", "resources" : ["shut.gif"] },
  {"word": "shun", "resources" : [] }
]
